{
  "posts": [
    {
      "id": "1",
      "title": "json-server",
      "userId": "1"
    },
    {
      "id": "2",
      "title": "json-server",
      "userId": "2"
    }
  ],
  "comments": [
    {
      "id": "1",
      "body": "some comment",
      "postId": "1"
    }
  ],
  "users": [
    {
      "id": "1",
      "username": "admin",
      "password": "123"
    }
  ],
  "profile": {
    "first": "Sergey",
    "lastname": "Romanov",
    "age": 29,
    "currency": "RUB",
    "country": "Russia",
    "city": "Bryansk",
    "username": "admin",
    "avatar": "https://c0.klipartz.com/pngpicture/407/87/sticker-png-kenny-mccormick-butters-stotch-tweek-tweak-clyde-donovan-kyle-broflovski-fictional-character-cartoon-fruit-kyle-broflovski-matt-stone.png"
  }
}